[
  {
    "Rank": "1",
    "Player": "Jarren Duran"
  },
  {
    "Rank": "2",
    "Player": "Rafael Devers"
  },
  {
    "Rank": "3",
    "Player": "Shohei Ohtani"
  },
  {
    "Rank": "4",
    "Player": "Bo Bichette"
  },
  {
    "Rank": "5",
    "Player": "Brent Rooker"
  },
  {
    "Rank": "6",
    "Player": "Jackson Chourio"
  },
  {
    "Rank": "7",
    "Player": "Francisco Lindor#"
  },
  {
    "Rank": "8",
    "Player": "Juan Soto"
  },
  {
    "Rank": "9",
    "Player": "Kyle Tucker"
  },
  {
    "Rank": "10",
    "Player": "Pete Alonso"
  },
  {
    "Rank": "11",
    "Player": "Corbin Carroll"
  },
  {
    "Rank": "12",
    "Player": "Lars Nootbaar"
  },
  {
    "Rank": "13",
    "Player": "Kyle Schwarber"
  },
  {
    "Rank": "14",
    "Player": "Aaron Judge"
  },
  {
    "Rank": "15",
    "Player": "Trea Turner"
  },
  {
    "Rank": "16",
    "Player": "Vladimir Guerrero Jr."
  },
  {
    "Rank": "17",
    "Player": "Austin Riley"
  },
  {
    "Rank": "18",
    "Player": "Julio Rodríguez"
  },
  {
    "Rank": "19",
    "Player": "Bobby Witt Jr."
  },
  {
    "Rank": "20",
    "Player": "Elly De La Cruz#"
  },
  {
    "Rank": "21",
    "Player": "Tyler Soderstrom"
  },
  {
    "Rank": "22",
    "Player": "James Wood"
  },
  {
    "Rank": "23",
    "Player": "Lawrence Butler"
  },
  {
    "Rank": "24",
    "Player": "Matt Olson"
  },
  {
    "Rank": "25",
    "Player": "Geraldo Perdomo#"
  },
  {
    "Rank": "26",
    "Player": "Bryan Reynolds#"
  },
  {
    "Rank": "27",
    "Player": "Pete Crow-Armstrong"
  },
  {
    "Rank": "28",
    "Player": "TJ Friedl"
  },
  {
    "Rank": "29",
    "Player": "Willy Adames"
  },
  {
    "Rank": "30",
    "Player": "Ozzie Albies#"
  },
  {
    "Rank": "31",
    "Player": "Cal Raleigh#"
  },
  {
    "Rank": "32",
    "Player": "Dansby Swanson"
  },
  {
    "Rank": "33",
    "Player": "Isaac Paredes"
  },
  {
    "Rank": "34",
    "Player": "Heliot Ramos"
  },
  {
    "Rank": "35",
    "Player": "Seiya Suzuki"
  },
  {
    "Rank": "36",
    "Player": "Jeremy Peña"
  },
  {
    "Rank": "37",
    "Player": "Randy Arozarena"
  },
  {
    "Rank": "38",
    "Player": "Vinnie Pasquantino"
  },
  {
    "Rank": "39",
    "Player": "Fernando Tatis Jr."
  },
  {
    "Rank": "40",
    "Player": "Brice Turang"
  },
  {
    "Rank": "41",
    "Player": "Brendan Donovan"
  },
  {
    "Rank": "42",
    "Player": "Steven Kwan"
  },
  {
    "Rank": "43",
    "Player": "Manny Machado"
  },
  {
    "Rank": "44",
    "Player": "Taylor Ward"
  },
  {
    "Rank": "45",
    "Player": "Nathaniel Lowe"
  },
  {
    "Rank": "46",
    "Player": "Marcell Ozuna"
  },
  {
    "Rank": "47",
    "Player": "Nick Castellanos"
  },
  {
    "Rank": "48",
    "Player": "Ian Happ#"
  },
  {
    "Rank": "49",
    "Player": "Eugenio Suárez"
  },
  {
    "Rank": "50",
    "Player": "Riley Greene"
  },
  {
    "Rank": "51",
    "Player": "Trevor Larnach"
  },
  {
    "Rank": "52",
    "Player": "Josh Naylor"
  },
  {
    "Rank": "53",
    "Player": "Yandy Díaz"
  },
  {
    "Rank": "54",
    "Player": "Spencer Torkelson"
  },
  {
    "Rank": "55",
    "Player": "Matt Chapman"
  },
  {
    "Rank": "56",
    "Player": "Jung Hoo Lee"
  },
  {
    "Rank": "57",
    "Player": "Jacob Wilson"
  },
  {
    "Rank": "58",
    "Player": "Christian Yelich"
  },
  {
    "Rank": "59",
    "Player": "J.P. Crawford"
  },
  {
    "Rank": "60",
    "Player": "Michael Harris II"
  },
  {
    "Rank": "61",
    "Player": "José Ramírez#"
  },
  {
    "Rank": "62",
    "Player": "Mookie Betts"
  },
  {
    "Rank": "63",
    "Player": "Trevor Story"
  },
  {
    "Rank": "64",
    "Player": "Jose Altuve"
  },
  {
    "Rank": "65",
    "Player": "Willson Contreras"
  },
  {
    "Rank": "66",
    "Player": "William Contreras"
  },
  {
    "Rank": "67",
    "Player": "Alec Bohm"
  },
  {
    "Rank": "68",
    "Player": "Maikel Garcia"
  },
  {
    "Rank": "69",
    "Player": "Paul Goldschmidt"
  },
  {
    "Rank": "70",
    "Player": "Nico Hoerner"
  },
  {
    "Rank": "71",
    "Player": "Nolan Schanuel"
  },
  {
    "Rank": "72",
    "Player": "Salvador Perez"
  },
  {
    "Rank": "73",
    "Player": "Christian Walker"
  },
  {
    "Rank": "74",
    "Player": "Lourdes Gurriel Jr."
  },
  {
    "Rank": "75",
    "Player": "Luis Arráez"
  },
  {
    "Rank": "76",
    "Player": "Junior Caminero"
  },
  {
    "Rank": "77",
    "Player": "Jonathan India"
  },
  {
    "Rank": "78",
    "Player": "Ryan McMahon"
  },
  {
    "Rank": "79",
    "Player": "Marcus Semien"
  },
  {
    "Rank": "80",
    "Player": "Anthony Volpe"
  },
  {
    "Rank": "81",
    "Player": "Miguel Vargas"
  },
  {
    "Rank": "82",
    "Player": "Nolan Arenado"
  },
  {
    "Rank": "83",
    "Player": "Xander Bogaerts"
  },
  {
    "Rank": "84",
    "Player": "Ty France"
  },
  {
    "Rank": "85",
    "Player": "Hunter Goodman"
  },
  {
    "Rank": "86",
    "Player": "Andy Pages"
  },
  {
    "Rank": "87",
    "Player": "Wilmer Flores"
  },
  {
    "Rank": "88",
    "Player": "Brandon Nimmo"
  },
  {
    "Rank": "89",
    "Player": "Sal Frelick"
  },
  {
    "Rank": "90",
    "Player": "Brandon Lowe"
  },
  {
    "Rank": "91",
    "Player": "Cody Bellinger"
  },
  {
    "Rank": "92",
    "Player": "Oneil Cruz"
  },
  {
    "Rank": "93",
    "Player": "Ke'Bryan Hayes"
  },
  {
    "Rank": "94",
    "Player": "Bryce Harper"
  },
  {
    "Rank": "95",
    "Player": "Carlos Santana#"
  },
  {
    "Rank": "96",
    "Player": "Bryson Stott"
  },
  {
    "Rank": "97",
    "Player": "Gunnar Henderson"
  },
  {
    "Rank": "98",
    "Player": "Max Muncy"
  },
  {
    "Rank": "99",
    "Player": "Rhys Hoskins"
  },
  {
    "Rank": "100",
    "Player": "George Springer"
  },
  {
    "Rank": "101",
    "Player": "Kristian Campbell"
  },
  {
    "Rank": "102",
    "Player": "Adley Rutschman#"
  },
  {
    "Rank": "103",
    "Player": "Jorge Soler"
  },
  {
    "Rank": "104",
    "Player": "Spencer Steer"
  },
  {
    "Rank": "105",
    "Player": "Eric Wagaman"
  },
  {
    "Rank": "106",
    "Player": "Freddie Freeman"
  },
  {
    "Rank": "107",
    "Player": "Wyatt Langford"
  },
  {
    "Rank": "108",
    "Player": "Ceddanne Rafaela"
  },
  {
    "Rank": "109",
    "Player": "Kyle Stowers"
  },
  {
    "Rank": "110",
    "Player": "Jackson Holliday"
  },
  {
    "Rank": "111",
    "Player": "Gabriel Arias"
  },
  {
    "Rank": "112",
    "Player": "Michael Busch"
  },
  {
    "Rank": "113",
    "Player": "Adolis García"
  },
  {
    "Rank": "114",
    "Player": "Luis Robert Jr."
  },
  {
    "Rank": "115",
    "Player": "Gleyber Torres"
  },
  {
    "Rank": "116",
    "Player": "Masyn Winn"
  },
  {
    "Rank": "117",
    "Player": "Matt McLain"
  },
  {
    "Rank": "118",
    "Player": "Wilyer Abreu"
  },
  {
    "Rank": "119",
    "Player": "Jonathan Aranda"
  },
  {
    "Rank": "120",
    "Player": "Andrew McCutchen"
  },
  {
    "Rank": "121",
    "Player": "Zach McKinstry"
  },
  {
    "Rank": "122",
    "Player": "CJ Abrams"
  },
  {
    "Rank": "123",
    "Player": "Kerry Carpenter"
  },
  {
    "Rank": "124",
    "Player": "Shea Langeliers"
  },
  {
    "Rank": "125",
    "Player": "Mike Yastrzemski"
  },
  {
    "Rank": "126",
    "Player": "Yainer Diaz"
  },
  {
    "Rank": "127",
    "Player": "Xavier Edwards#"
  },
  {
    "Rank": "128",
    "Player": "Joey Ortiz"
  },
  {
    "Rank": "129",
    "Player": "Gavin Lux"
  },
  {
    "Rank": "130",
    "Player": "Gavin Sheets"
  },
  {
    "Rank": "131",
    "Player": "Alex Bregman"
  },
  {
    "Rank": "132",
    "Player": "Brenton Doyle"
  },
  {
    "Rank": "133",
    "Player": "Josh Jung"
  },
  {
    "Rank": "134",
    "Player": "Michael Conforto"
  },
  {
    "Rank": "135",
    "Player": "Jake Meyers"
  },
  {
    "Rank": "136",
    "Player": "J.T. Realmuto"
  },
  {
    "Rank": "137",
    "Player": "Victor Scott II"
  },
  {
    "Rank": "138",
    "Player": "Luis García Jr."
  },
  {
    "Rank": "139",
    "Player": "Ryan O'Hearn"
  },
  {
    "Rank": "140",
    "Player": "Keibert Ruiz#"
  },
  {
    "Rank": "141",
    "Player": "Max Kepler"
  },
  {
    "Rank": "142",
    "Player": "Josh Smith"
  },
  {
    "Rank": "143",
    "Player": "Jordan Beck"
  },
  {
    "Rank": "144",
    "Player": "Ernie Clement"
  },
  {
    "Rank": "145",
    "Player": "Kyle Manzardo"
  },
  {
    "Rank": "146",
    "Player": "Ben Rice"
  },
  {
    "Rank": "147",
    "Player": "Josh Bell#"
  },
  {
    "Rank": "148",
    "Player": "Teoscar Hernández"
  },
  {
    "Rank": "149",
    "Player": "Byron Buxton"
  },
  {
    "Rank": "150",
    "Player": "Trent Grisham"
  },
  {
    "Rank": "151",
    "Player": "Luis Rengifo#"
  },
  {
    "Rank": "152",
    "Player": "Carlos Correa"
  },
  {
    "Rank": "153",
    "Player": "Alejandro Kirk"
  },
  {
    "Rank": "154",
    "Player": "Will Smith"
  },
  {
    "Rank": "155",
    "Player": "Cedric Mullins"
  },
  {
    "Rank": "156",
    "Player": "Austin Wells"
  },
  {
    "Rank": "157",
    "Player": "Jake Burger"
  },
  {
    "Rank": "158",
    "Player": "Trey Sweeney"
  },
  {
    "Rank": "159",
    "Player": "Jasson Domínguez#"
  },
  {
    "Rank": "160",
    "Player": "Santiago Espinal"
  },
  {
    "Rank": "161",
    "Player": "Michael Massey"
  },
  {
    "Rank": "162",
    "Player": "Logan O'Hoppe"
  },
  {
    "Rank": "163",
    "Player": "Anthony Santander#"
  },
  {
    "Rank": "164",
    "Player": "Mark Vientos"
  },
  {
    "Rank": "165",
    "Player": "JJ Bleday"
  },
  {
    "Rank": "166",
    "Player": "Zach Neto"
  },
  {
    "Rank": "167",
    "Player": "Lenyn Sosa"
  },
  {
    "Rank": "168",
    "Player": "Michael Toglia#"
  },
  {
    "Rank": "169",
    "Player": "Adam Frazier"
  },
  {
    "Rank": "170",
    "Player": "Ryan Jeffers"
  },
  {
    "Rank": "171",
    "Player": "Javier Báez"
  },
  {
    "Rank": "172",
    "Player": "Isiah Kiner-Falefa"
  },
  {
    "Rank": "173",
    "Player": "Otto López"
  },
  {
    "Rank": "174",
    "Player": "Ryan Mountcastle"
  },
  {
    "Rank": "175",
    "Player": "Jo Adell"
  },
  {
    "Rank": "176",
    "Player": "Tommy Edman#"
  },
  {
    "Rank": "177",
    "Player": "Tyrone Taylor"
  },
  {
    "Rank": "178",
    "Player": "Colt Keith"
  },
  {
    "Rank": "179",
    "Player": "Carlos Narváez"
  },
  {
    "Rank": "180",
    "Player": "Pavin Smith"
  },
  {
    "Rank": "181",
    "Player": "Jorge Polanco#"
  },
  {
    "Rank": "182",
    "Player": "Andrew Vaughn"
  },
  {
    "Rank": "183",
    "Player": "Luis Urías"
  },
  {
    "Rank": "184",
    "Player": "Alec Burleson"
  },
  {
    "Rank": "185",
    "Player": "Ángel Martínez#"
  },
  {
    "Rank": "186",
    "Player": "Jesús Sánchez"
  },
  {
    "Rank": "187",
    "Player": "Cam Smith"
  },
  {
    "Rank": "188",
    "Player": "Dillon Dingler"
  },
  {
    "Rank": "189",
    "Player": "Kameron Misner"
  },
  {
    "Rank": "190",
    "Player": "Brooks Lee#"
  },
  {
    "Rank": "191",
    "Player": "Nick Allen"
  },
  {
    "Rank": "192",
    "Player": "Harrison Bader"
  },
  {
    "Rank": "193",
    "Player": "Bo Naylor"
  },
  {
    "Rank": "194",
    "Player": "Alek Thomas"
  },
  {
    "Rank": "195",
    "Player": "Miguel Andujar"
  },
  {
    "Rank": "196",
    "Player": "Patrick Bailey#"
  },
  {
    "Rank": "197",
    "Player": "Chase Meidroth"
  },
  {
    "Rank": "198",
    "Player": "Gabriel Moreno"
  },
  {
    "Rank": "199",
    "Player": "Leody Taveras#"
  },
  {
    "Rank": "199",
    "Player": "Leody Taveras#"
  },
  {
    "Rank": "199",
    "Player": "Leody Taveras#"
  },
  {
    "Rank": "200",
    "Player": "Jonah Heim#"
  },
  {
    "Rank": "201",
    "Player": "Willi Castro#"
  },
  {
    "Rank": "202",
    "Player": "Agustín Ramírez"
  },
  {
    "Rank": "203",
    "Player": "Ketel Marte#"
  },
  {
    "Rank": "204",
    "Player": "José Caballero"
  },
  {
    "Rank": "205",
    "Player": "Caleb Durbin"
  },
  {
    "Rank": "206",
    "Player": "Jackson Merrill"
  },
  {
    "Rank": "207",
    "Player": "Drew Waters#"
  },
  {
    "Rank": "208",
    "Player": "Dylan Crews"
  },
  {
    "Rank": "209",
    "Player": "Mickey Moniak"
  },
  {
    "Rank": "210",
    "Player": "Jordan Walker"
  },
  {
    "Rank": "211",
    "Player": "Ben Williamson"
  },
  {
    "Rank": "212",
    "Player": "Nolan Jones"
  },
  {
    "Rank": "213",
    "Player": "Connor Norby"
  },
  {
    "Rank": "214",
    "Player": "Taylor Walls#"
  },
  {
    "Rank": "215",
    "Player": "Joey Bart"
  },
  {
    "Rank": "216",
    "Player": "Kyle Farmer"
  },
  {
    "Rank": "217",
    "Player": "Ramón Urías"
  },
  {
    "Rank": "218",
    "Player": "LaMonte Wade Jr."
  },
  {
    "Rank": "219",
    "Player": "Andrés Giménez"
  },
  {
    "Rank": "220",
    "Player": "Kyle Isbel"
  },
  {
    "Rank": "221",
    "Player": "Heston Kjerstad"
  },
  {
    "Rank": "222",
    "Player": "Andrew Benintendi"
  },
  {
    "Rank": "223",
    "Player": "Tyler Fitzgerald"
  },
  {
    "Rank": "224",
    "Player": "Rowdy Tellez"
  },
  {
    "Rank": "225",
    "Player": "Mike Trout"
  },
  {
    "Rank": "226",
    "Player": "Alex Verdugo"
  },
  {
    "Rank": "227",
    "Player": "Tommy Pham"
  },
  {
    "Rank": "228",
    "Player": "Addison Barger"
  },
  {
    "Rank": "229",
    "Player": "Pedro Pagés"
  },
  {
    "Rank": "230",
    "Player": "Jake Cronenworth"
  },
  {
    "Rank": "231",
    "Player": "Danny Jansen"
  },
  {
    "Rank": "232",
    "Player": "Daniel Schneemann"
  },
  {
    "Rank": "233",
    "Player": "Carson Kelly"
  },
  {
    "Rank": "234",
    "Player": "Brett Baty"
  },
  {
    "Rank": "235",
    "Player": "Sean Murphy"
  },
  {
    "Rank": "236",
    "Player": "Dylan Moore"
  },
  {
    "Rank": "237",
    "Player": "Christopher Morel"
  },
  {
    "Rank": "238",
    "Player": "Eli White"
  },
  {
    "Rank": "239",
    "Player": "Alex Call"
  },
  {
    "Rank": "240",
    "Player": "Jazz Chisholm Jr."
  },
  {
    "Rank": "241",
    "Player": "Elias Díaz"
  },
  {
    "Rank": "242",
    "Player": "Javier Sanoja"
  },
  {
    "Rank": "243",
    "Player": "Corey Seager"
  },
  {
    "Rank": "244",
    "Player": "Luisangel Acuña"
  },
  {
    "Rank": "245",
    "Player": "Kiké Hernández"
  },
  {
    "Rank": "246",
    "Player": "Edgar Quero#"
  },
  {
    "Rank": "247",
    "Player": "Joc Pederson"
  },
  {
    "Rank": "248",
    "Player": "Matt Shaw"
  },
  {
    "Rank": "249",
    "Player": "Victor Caratini#"
  },
  {
    "Rank": "250",
    "Player": "Nathan Lukes"
  },
  {
    "Rank": "251",
    "Player": "Brooks Baldwin#"
  },
  {
    "Rank": "252",
    "Player": "Iván Herrera"
  },
  {
    "Rank": "253",
    "Player": "José Tena"
  },
  {
    "Rank": "254",
    "Player": "Kyren Paris"
  },
  {
    "Rank": "255",
    "Player": "Joshua Palacios"
  },
  {
    "Rank": "256",
    "Player": "Ezequiel Tovar"
  },
  {
    "Rank": "257",
    "Player": "Drake Baldwin"
  },
  {
    "Rank": "258",
    "Player": "Alexander Canario"
  },
  {
    "Rank": "259",
    "Player": "Brandon Marsh"
  },
  {
    "Rank": "260",
    "Player": "Jose Iglesias"
  },
  {
    "Rank": "261",
    "Player": "Starling Marte"
  },
  {
    "Rank": "262",
    "Player": "Isaac Collins#"
  },
  {
    "Rank": "263",
    "Player": "Matt Mervis"
  },
  {
    "Rank": "264",
    "Player": "Jose Trevino"
  },
  {
    "Rank": "265",
    "Player": "Chandler Simpson"
  },
  {
    "Rank": "266",
    "Player": "Jacob Young"
  },
  {
    "Rank": "267",
    "Player": "Tim Tawa"
  },
  {
    "Rank": "268",
    "Player": "Austin Hays"
  },
  {
    "Rank": "269",
    "Player": "Liam Hicks"
  },
  {
    "Rank": "270",
    "Player": "Matt Thaiss"
  },
  {
    "Rank": "270",
    "Player": "Matt Thaiss"
  },
  {
    "Rank": "270",
    "Player": "Matt Thaiss"
  },
  {
    "Rank": "271",
    "Player": "Jeff McNeil"
  },
  {
    "Rank": "272",
    "Player": "Michael A. Taylor"
  },
  {
    "Rank": "273",
    "Player": "Tyler Stephenson"
  },
  {
    "Rank": "274",
    "Player": "Miles Mastrobuoni"
  },
  {
    "Rank": "275",
    "Player": "Johan Rojas"
  },
  {
    "Rank": "276",
    "Player": "Nolan Gorman"
  },
  {
    "Rank": "277",
    "Player": "Dane Myers"
  },
  {
    "Rank": "278",
    "Player": "Oswaldo Cabrera#"
  },
  {
    "Rank": "279",
    "Player": "Luis Torrens"
  },
  {
    "Rank": "280",
    "Player": "Yordan Alvarez"
  },
  {
    "Rank": "281",
    "Player": "Jake Fraley"
  },
  {
    "Rank": "282",
    "Player": "Ramón Laureano"
  },
  {
    "Rank": "283",
    "Player": "Myles Straw"
  },
  {
    "Rank": "284",
    "Player": "Jared Triolo"
  },
  {
    "Rank": "285",
    "Player": "Mauricio Dubón"
  },
  {
    "Rank": "286",
    "Player": "Freddy Fermin"
  },
  {
    "Rank": "287",
    "Player": "Mitch Garver"
  },
  {
    "Rank": "288",
    "Player": "Brendan Rodgers"
  },
  {
    "Rank": "289",
    "Player": "Nick Kurtz"
  },
  {
    "Rank": "290",
    "Player": "Justyn-Henry Malloy"
  },
  {
    "Rank": "291",
    "Player": "Jake Mangum#"
  },
  {
    "Rank": "292",
    "Player": "Francisco Alvarez"
  },
  {
    "Rank": "293",
    "Player": "Yoán Moncada#"
  },
  {
    "Rank": "294",
    "Player": "Triston Casas"
  },
  {
    "Rank": "295",
    "Player": "Nick Martini"
  },
  {
    "Rank": "296",
    "Player": "Christian Vázquez"
  },
  {
    "Rank": "297",
    "Player": "Kyle Higashioka"
  },
  {
    "Rank": "298",
    "Player": "Oswald Peraza"
  },
  {
    "Rank": "299",
    "Player": "Zach Dezenzo"
  },
  {
    "Rank": "300",
    "Player": "Hunter Renfroe"
  },
  {
    "Rank": "301",
    "Player": "Amed Rosario"
  },
  {
    "Rank": "302",
    "Player": "Jake Bauers"
  },
  {
    "Rank": "303",
    "Player": "Jhonkensy Noel"
  },
  {
    "Rank": "304",
    "Player": "Gio Urshela"
  },
  {
    "Rank": "305",
    "Player": "Kody Clemens"
  },
  {
    "Rank": "305",
    "Player": "Kody Clemens"
  },
  {
    "Rank": "305",
    "Player": "Kody Clemens"
  },
  {
    "Rank": "306",
    "Player": "Andy Ibáñez"
  },
  {
    "Rank": "307",
    "Player": "Josh Rojas"
  },
  {
    "Rank": "308",
    "Player": "Justin Turner"
  },
  {
    "Rank": "309",
    "Player": "Jonah Bride"
  },
  {
    "Rank": "309",
    "Player": "Jonah Bride"
  },
  {
    "Rank": "309",
    "Player": "Jonah Bride"
  },
  {
    "Rank": "310",
    "Player": "Edouard Julien"
  },
  {
    "Rank": "311",
    "Player": "Edmundo Sosa"
  },
  {
    "Rank": "312",
    "Player": "Adael Amador#"
  },
  {
    "Rank": "313",
    "Player": "Royce Lewis"
  },
  {
    "Rank": "314",
    "Player": "Curtis Mead"
  },
  {
    "Rank": "315",
    "Player": "Brayan Rocchio#"
  },
  {
    "Rank": "316",
    "Player": "Enmanuel Valdéz"
  },
  {
    "Rank": "317",
    "Player": "Tyler Wade"
  },
  {
    "Rank": "318",
    "Player": "Jordan Westburg"
  },
  {
    "Rank": "319",
    "Player": "Travis d'Arnaud"
  },
  {
    "Rank": "320",
    "Player": "Matt Wallner"
  },
  {
    "Rank": "321",
    "Player": "Miguel Amaya"
  },
  {
    "Rank": "322",
    "Player": "Randal Grichuk"
  },
  {
    "Rank": "323",
    "Player": "Daulton Varsho"
  },
  {
    "Rank": "324",
    "Player": "Miguel Rojas"
  },
  {
    "Rank": "325",
    "Player": "Will Benson"
  },
  {
    "Rank": "326",
    "Player": "Martín Maldonado"
  },
  {
    "Rank": "327",
    "Player": "Josh Lowe"
  },
  {
    "Rank": "328",
    "Player": "Max Muncy"
  },
  {
    "Rank": "329",
    "Player": "Alan Roden"
  },
  {
    "Rank": "330",
    "Player": "Jason Heyward"
  },
  {
    "Rank": "331",
    "Player": "Abraham Toro#"
  },
  {
    "Rank": "332",
    "Player": "Mark Canha"
  },
  {
    "Rank": "333",
    "Player": "Tyler O'Neill"
  },
  {
    "Rank": "334",
    "Player": "Jacob Stallings"
  },
  {
    "Rank": "335",
    "Player": "Henry Davis"
  },
  {
    "Rank": "336",
    "Player": "Jeimer Candelario#"
  },
  {
    "Rank": "337",
    "Player": "Tim Anderson"
  },
  {
    "Rank": "338",
    "Player": "David Hamilton"
  },
  {
    "Rank": "339",
    "Player": "Graham Pauley"
  },
  {
    "Rank": "340",
    "Player": "Donovan Solano"
  },
  {
    "Rank": "341",
    "Player": "José Herrera#"
  },
  {
    "Rank": "342",
    "Player": "Brandon Lockridge"
  },
  {
    "Rank": "343",
    "Player": "Mike Tauchman"
  },
  {
    "Rank": "344",
    "Player": "Romy González"
  },
  {
    "Rank": "345",
    "Player": "Luke Raley"
  },
  {
    "Rank": "346",
    "Player": "Cavan Biggio"
  },
  {
    "Rank": "347",
    "Player": "Christian Encarnacion-Strand"
  },
  {
    "Rank": "348",
    "Player": "Max Schuemann"
  },
  {
    "Rank": "349",
    "Player": "Jon Berti"
  },
  {
    "Rank": "350",
    "Player": "Derek Hill"
  },
  {
    "Rank": "351",
    "Player": "Spencer Horwitz"
  },
  {
    "Rank": "352",
    "Player": "Rob Refsnyder"
  },
  {
    "Rank": "353",
    "Player": "Nick Fortes"
  },
  {
    "Rank": "354",
    "Player": "Garrett Mitchell"
  },
  {
    "Rank": "355",
    "Player": "Jesse Winker"
  },
  {
    "Rank": "356",
    "Player": "Dylan Carlson#"
  },
  {
    "Rank": "357",
    "Player": "Sam Haggerty#"
  },
  {
    "Rank": "358",
    "Player": "Luis Matos"
  },
  {
    "Rank": "359",
    "Player": "Emmanuel Rivera"
  },
  {
    "Rank": "360",
    "Player": "Vinny Capra"
  },
  {
    "Rank": "360",
    "Player": "Vinny Capra"
  },
  {
    "Rank": "360",
    "Player": "Vinny Capra"
  },
  {
    "Rank": "361",
    "Player": "Blake Dunn"
  },
  {
    "Rank": "362",
    "Player": "Tyler Freeman"
  },
  {
    "Rank": "363",
    "Player": "DJ LeMahieu"
  },
  {
    "Rank": "364",
    "Player": "Ronald Acuña Jr."
  },
  {
    "Rank": "365",
    "Player": "Sean Bouchard"
  },
  {
    "Rank": "366",
    "Player": "Seth Brown"
  },
  {
    "Rank": "367",
    "Player": "Jonatan Clase#"
  },
  {
    "Rank": "368",
    "Player": "Noelvi Marté"
  },
  {
    "Rank": "369",
    "Player": "Leo Rivas#"
  },
  {
    "Rank": "370",
    "Player": "Christian Koss"
  },
  {
    "Rank": "371",
    "Player": "Griffin Conine"
  },
  {
    "Rank": "372",
    "Player": "Ben Rortvedt"
  },
  {
    "Rank": "373",
    "Player": "Lane Thomas"
  },
  {
    "Rank": "374",
    "Player": "Chris Taylor"
  },
  {
    "Rank": "374",
    "Player": "Chris Taylor"
  },
  {
    "Rank": "374",
    "Player": "Chris Taylor"
  },
  {
    "Rank": "375",
    "Player": "Jacob Amaya"
  },
  {
    "Rank": "376",
    "Player": "Will Wagner"
  },
  {
    "Rank": "377",
    "Player": "Connor Wong"
  },
  {
    "Rank": "378",
    "Player": "DaShawn Keirsey Jr."
  },
  {
    "Rank": "379",
    "Player": "Hyeseong Kim"
  },
  {
    "Rank": "380",
    "Player": "J.C. Escarra"
  },
  {
    "Rank": "381",
    "Player": "Jarred Kelenic"
  },
  {
    "Rank": "382",
    "Player": "Jorge Mateo"
  },
  {
    "Rank": "383",
    "Player": "Kevin Newman"
  },
  {
    "Rank": "384",
    "Player": "Robert Hassell III"
  },
  {
    "Rank": "385",
    "Player": "Nick Maton"
  },
  {
    "Rank": "386",
    "Player": "Casey Schmitt"
  },
  {
    "Rank": "387",
    "Player": "Oscar González"
  },
  {
    "Rank": "388",
    "Player": "Austin Hedges"
  },
  {
    "Rank": "389",
    "Player": "Yohel Pozo"
  },
  {
    "Rank": "390",
    "Player": "Tyler Heineman#"
  },
  {
    "Rank": "391",
    "Player": "Will Wilson"
  },
  {
    "Rank": "392",
    "Player": "Sam Huff"
  },
  {
    "Rank": "393",
    "Player": "Denzel Clarke"
  },
  {
    "Rank": "394",
    "Player": "Paul DeJong"
  },
  {
    "Rank": "395",
    "Player": "Endy Rodríguez#"
  },
  {
    "Rank": "396",
    "Player": "Garrett Hampson"
  },
  {
    "Rank": "396",
    "Player": "Garrett Hampson"
  },
  {
    "Rank": "396",
    "Player": "Garrett Hampson"
  },
  {
    "Rank": "397",
    "Player": "Evan Carter"
  },
  {
    "Rank": "398",
    "Player": "Tim Elko"
  },
  {
    "Rank": "399",
    "Player": "Ronny Simón#"
  },
  {
    "Rank": "400",
    "Player": "Orlando Arcia"
  },
  {
    "Rank": "400",
    "Player": "Orlando Arcia"
  },
  {
    "Rank": "400",
    "Player": "Orlando Arcia"
  },
  {
    "Rank": "401",
    "Player": "Jace Jung"
  },
  {
    "Rank": "402",
    "Player": "Chas McCormick"
  },
  {
    "Rank": "403",
    "Player": "Nick Sogard#"
  },
  {
    "Rank": "404",
    "Player": "Jorbit Vivas"
  },
  {
    "Rank": "405",
    "Player": "MJ Melendez"
  },
  {
    "Rank": "406",
    "Player": "Bryan De La Cruz"
  },
  {
    "Rank": "407",
    "Player": "Rafael Marchán#"
  },
  {
    "Rank": "408",
    "Player": "Nasim Nuñez#"
  },
  {
    "Rank": "409",
    "Player": "Connor Joe"
  },
  {
    "Rank": "409",
    "Player": "Connor Joe"
  },
  {
    "Rank": "409",
    "Player": "Connor Joe"
  },
  {
    "Rank": "410",
    "Player": "Travis Jankowski"
  },
  {
    "Rank": "410",
    "Player": "Travis Jankowski"
  },
  {
    "Rank": "410",
    "Player": "Travis Jankowski"
  },
  {
    "Rank": "411",
    "Player": "Riley Adams"
  },
  {
    "Rank": "412",
    "Player": "Eric Haase"
  },
  {
    "Rank": "413",
    "Player": "Jake McCarthy"
  },
  {
    "Rank": "414",
    "Player": "Austin Wynns"
  },
  {
    "Rank": "414",
    "Player": "Austin Wynns"
  },
  {
    "Rank": "414",
    "Player": "Austin Wynns"
  },
  {
    "Rank": "415",
    "Player": "Jhonny Pereda"
  },
  {
    "Rank": "416",
    "Player": "Víctor Robles"
  },
  {
    "Rank": "417",
    "Player": "Austin Slater"
  },
  {
    "Rank": "418",
    "Player": "Jack Suwinski"
  },
  {
    "Rank": "419",
    "Player": "Austin Barnes"
  },
  {
    "Rank": "420",
    "Player": "Colton Cowser"
  },
  {
    "Rank": "421",
    "Player": "Ryan Kreidler"
  },
  {
    "Rank": "422",
    "Player": "Marcelo Mayer"
  },
  {
    "Rank": "423",
    "Player": "Thomas Saggese"
  },
  {
    "Rank": "424",
    "Player": "Maverick Handley"
  },
  {
    "Rank": "425",
    "Player": "Matthew Lugo"
  },
  {
    "Rank": "426",
    "Player": "Kevin Pillar"
  },
  {
    "Rank": "427",
    "Player": "Alan Trejo"
  },
  {
    "Rank": "428",
    "Player": "Matt Gorski"
  },
  {
    "Rank": "429",
    "Player": "Luken Baker"
  },
  {
    "Rank": "430",
    "Player": "Kris Bryant"
  },
  {
    "Rank": "431",
    "Player": "Daz Cameron"
  },
  {
    "Rank": "432",
    "Player": "Oliver Dunn"
  },
  {
    "Rank": "433",
    "Player": "Wenceel Pérez#"
  },
  {
    "Rank": "434",
    "Player": "Jake Rogers"
  },
  {
    "Rank": "435",
    "Player": "Weston Wilson"
  },
  {
    "Rank": "436",
    "Player": "Ezequiel Durán"
  },
  {
    "Rank": "437",
    "Player": "Yuli Gurriel"
  },
  {
    "Rank": "438",
    "Player": "Ryan Bliss"
  },
  {
    "Rank": "439",
    "Player": "Mickey Gasper#"
  },
  {
    "Rank": "440",
    "Player": "Thairo Estrada"
  },
  {
    "Rank": "441",
    "Player": "Dustin Harris"
  },
  {
    "Rank": "442",
    "Player": "Dalton Rushing"
  },
  {
    "Rank": "443",
    "Player": "Coby Mayo"
  },
  {
    "Rank": "444",
    "Player": "Tomás Nido"
  },
  {
    "Rank": "445",
    "Player": "Zac Veen"
  },
  {
    "Rank": "446",
    "Player": "Cole Young"
  },
  {
    "Rank": "447",
    "Player": "Stuart Fairchild"
  },
  {
    "Rank": "448",
    "Player": "Daylen Lile"
  },
  {
    "Rank": "449",
    "Player": "José Miranda"
  },
  {
    "Rank": "450",
    "Player": "Gary Sánchez"
  },
  {
    "Rank": "451",
    "Player": "Davis Schneider"
  },
  {
    "Rank": "452",
    "Player": "Nick Gonzales"
  },
  {
    "Rank": "453",
    "Player": "Nick Loftin"
  },
  {
    "Rank": "454",
    "Player": "Parker Meadows"
  },
  {
    "Rank": "455",
    "Player": "Alejandro Osuna"
  },
  {
    "Rank": "456",
    "Player": "Korey Lee"
  },
  {
    "Rank": "457",
    "Player": "Andruw Monasterio"
  },
  {
    "Rank": "458",
    "Player": "Pablo Reyes"
  },
  {
    "Rank": "459",
    "Player": "Jac Caglianone"
  },
  {
    "Rank": "460",
    "Player": "Aaron Schunk"
  },
  {
    "Rank": "461",
    "Player": "Hayden Senger"
  },
  {
    "Rank": "462",
    "Player": "Nicky Lopez"
  },
  {
    "Rank": "462",
    "Player": "Nicky Lopez"
  },
  {
    "Rank": "462",
    "Player": "Nicky Lopez"
  },
  {
    "Rank": "463",
    "Player": "Reese McGuire"
  },
  {
    "Rank": "464",
    "Player": "James Outman"
  },
  {
    "Rank": "465",
    "Player": "Luke Keaschall"
  },
  {
    "Rank": "466",
    "Player": "Jonny DeLuca"
  },
  {
    "Rank": "467",
    "Player": "Willie MacIver"
  },
  {
    "Rank": "468",
    "Player": "Jacob Melton"
  },
  {
    "Rank": "469",
    "Player": "Michael Stefanic"
  },
  {
    "Rank": "470",
    "Player": "David Villar"
  },
  {
    "Rank": "471",
    "Player": "Logan Davidson#"
  },
  {
    "Rank": "472",
    "Player": "Sam Hilliard"
  },
  {
    "Rank": "473",
    "Player": "Ronny Mauricio#"
  },
  {
    "Rank": "474",
    "Player": "Jose Siri"
  },
  {
    "Rank": "475",
    "Player": "David Fry"
  },
  {
    "Rank": "476",
    "Player": "Jordan Lawlar"
  },
  {
    "Rank": "477",
    "Player": "Dominic Smith"
  },
  {
    "Rank": "478",
    "Player": "Jared Young"
  },
  {
    "Rank": "479",
    "Player": "Jose Barrero"
  },
  {
    "Rank": "480",
    "Player": "Vidal Bruján#"
  },
  {
    "Rank": "481",
    "Player": "Bobby Dalbec"
  },
  {
    "Rank": "482",
    "Player": "Heriberto Hernández"
  },
  {
    "Rank": "483",
    "Player": "John Rave"
  },
  {
    "Rank": "484",
    "Player": "José Azócar"
  },
  {
    "Rank": "484",
    "Player": "José Azócar"
  },
  {
    "Rank": "484",
    "Player": "José Azócar"
  },
  {
    "Rank": "485",
    "Player": "Luis Campusano"
  },
  {
    "Rank": "486",
    "Player": "Rece Hinds"
  },
  {
    "Rank": "487",
    "Player": "Manuel Margot"
  },
  {
    "Rank": "488",
    "Player": "Akil Baddoo"
  },
  {
    "Rank": "489",
    "Player": "Moisés Ballesteros"
  },
  {
    "Rank": "490",
    "Player": "Blake Sabol"
  },
  {
    "Rank": "491",
    "Player": "CJ Alexander"
  },
  {
    "Rank": "492",
    "Player": "Scott Kingery"
  },
  {
    "Rank": "493",
    "Player": "Owen Miller"
  },
  {
    "Rank": "494",
    "Player": "Ryan Ritter"
  },
  {
    "Rank": "495",
    "Player": "Michael Siani"
  },
  {
    "Rank": "496",
    "Player": "Gage Workman"
  },
  {
    "Rank": "496",
    "Player": "Gage Workman"
  },
  {
    "Rank": "496",
    "Player": "Gage Workman"
  },
  {
    "Rank": "497",
    "Player": "Jorge Barrosa#"
  },
  {
    "Rank": "498",
    "Player": "Daniel Johnson"
  },
  {
    "Rank": "499",
    "Player": "Tirso Ornelas"
  },
  {
    "Rank": "500",
    "Player": "Jurickson Profar#"
  },
  {
    "Rank": "501",
    "Player": "Drew Avans"
  },
  {
    "Rank": "502",
    "Player": "Tucker Barnhart"
  },
  {
    "Rank": "503",
    "Player": "Jacob Hurtubise"
  },
  {
    "Rank": "504",
    "Player": "Otto Kemp"
  },
  {
    "Rank": "505",
    "Player": "Ryan Vilade"
  },
  {
    "Rank": "506",
    "Player": "Luke Williams"
  },
  {
    "Rank": "507",
    "Player": "Jerar Encarnación"
  },
  {
    "Rank": "508",
    "Player": "Keston Hiura"
  },
  {
    "Rank": "509",
    "Player": "Johnathan Rodríguez"
  },
  {
    "Rank": "510",
    "Player": "Kyle Teel"
  },
  {
    "Rank": "511",
    "Player": "Will Brennan"
  },
  {
    "Rank": "512",
    "Player": "Blaine Crim"
  },
  {
    "Rank": "513",
    "Player": "Ji Hwan Bae"
  },
  {
    "Rank": "514",
    "Player": "Gustavo Campero#"
  },
  {
    "Rank": "515",
    "Player": "Braxton Fulford"
  },
  {
    "Rank": "516",
    "Player": "Brett Wisely"
  },
  {
    "Rank": "517",
    "Player": "Ali Sánchez"
  },
  {
    "Rank": "518",
    "Player": "Nick Solak"
  },
  {
    "Rank": "519",
    "Player": "Ildemaro Vargas#"
  },
  {
    "Rank": "520",
    "Player": "Matt Vierling"
  },
  {
    "Rank": "521",
    "Player": "Nick Ahmed"
  },
  {
    "Rank": "522",
    "Player": "Dominic Canzone"
  },
  {
    "Rank": "523",
    "Player": "Andrew Knizner"
  },
  {
    "Rank": "524",
    "Player": "Luke Maile"
  },
  {
    "Rank": "525",
    "Player": "Víctor Mesa Jr."
  },
  {
    "Rank": "526",
    "Player": "Coco Montes"
  },
  {
    "Rank": "527",
    "Player": "Omar Narváez"
  },
  {
    "Rank": "528",
    "Player": "Liover Peguero"
  },
  {
    "Rank": "529",
    "Player": "Rhylan Thomas"
  },
  {
    "Rank": "530",
    "Player": "Chadwick Tromp"
  },
  {
    "Rank": "530",
    "Player": "Chadwick Tromp"
  },
  {
    "Rank": "530",
    "Player": "Chadwick Tromp"
  },
  {
    "Rank": "531",
    "Player": "Roman Anthony"
  },
  {
    "Rank": "532",
    "Player": "J.D. Davis"
  },
  {
    "Rank": "533",
    "Player": "Samad Taylor"
  },
  {
    "Rank": "534",
    "Player": "Dairon Blanco"
  },
  {
    "Rank": "535",
    "Player": "Cal Stevenson"
  },
  {
    "Rank": "536",
    "Player": "Eddie Rosario"
  },
  {
    "Rank": "536",
    "Player": "Eddie Rosario"
  },
  {
    "Rank": "536",
    "Player": "Eddie Rosario"
  },
  {
    "Rank": "537",
    "Player": "Rob Brantly"
  },
  {
    "Rank": "538",
    "Player": "Tsung-Che Cheng"
  },
  {
    "Rank": "539",
    "Player": "Tyler Tolbert"
  },
  {
    "Rank": "540",
    "Player": "Tyler Callihan"
  },
  {
    "Rank": "541",
    "Player": "Jahmai Jones"
  },
  {
    "Rank": "542",
    "Player": "Carson McCusker"
  },
  {
    "Rank": "543",
    "Player": "Jonathan Ornelas"
  },
  {
    "Rank": "544",
    "Player": "Mason McCoy"
  },
  {
    "Rank": "545",
    "Player": "Shay Whitcomb"
  },
  {
    "Rank": "546",
    "Player": "Jack Winkler"
  },
  {
    "Rank": "547",
    "Player": "Brewer Hicklen"
  },
  {
    "Rank": "548",
    "Player": "Trey Lipscomb"
  },
  {
    "Rank": "549",
    "Player": "Richie Palacios"
  },
  {
    "Rank": "550",
    "Player": "Brett Sullivan"
  },
  {
    "Rank": "551",
    "Player": "Hunter Feduccia"
  },
  {
    "Rank": "552",
    "Player": "Ryan Fitzgerald"
  },
  {
    "Rank": "553",
    "Player": "Dom Nuñez"
  },
  {
    "Rank": "554",
    "Player": "César Salazar"
  },
  {
    "Rank": "555",
    "Player": "Andrés Chaparro"
  },
  {
    "Rank": "556",
    "Player": "Greg Jones#"
  },
  {
    "Rank": "557",
    "Player": "Jordyn Adams"
  },
  {
    "Rank": "558",
    "Player": "Cooper Hummel#"
  },
  {
    "Rank": "559",
    "Player": "Niko Kavadas"
  },
  {
    "Rank": "560",
    "Player": "Ryne Nelson"
  },
  {
    "Rank": "561",
    "Player": "Colin Rea"
  },
  {
    "Rank": "562",
    "Player": "Zach Agnos"
  },
  {
    "Rank": "563",
    "Player": "Jake Bird"
  },
  {
    "Rank": "564",
    "Player": "Hayden Birdsong"
  },
  {
    "Rank": "565",
    "Player": "Matt Bowman"
  },
  {
    "Rank": "566",
    "Player": "John Brebbia"
  },
  {
    "Rank": "567",
    "Player": "Yennier Cano"
  },
  {
    "Rank": "568",
    "Player": "Angel Chivilli"
  },
  {
    "Rank": "569",
    "Player": "Emmanuel Clase"
  },
  {
    "Rank": "570",
    "Player": "Yerry De los Santos"
  },
  {
    "Rank": "571",
    "Player": "Seranthony Domínguez"
  },
  {
    "Rank": "572",
    "Player": "Jhoan Durán"
  },
  {
    "Rank": "573",
    "Player": "Carlos Estévez"
  },
  {
    "Rank": "574",
    "Player": "Aramis Garcia"
  },
  {
    "Rank": "575",
    "Player": "Yimi García"
  },
  {
    "Rank": "576",
    "Player": "Seth Halvorsen"
  },
  {
    "Rank": "577",
    "Player": "Ryan Helsley"
  },
  {
    "Rank": "578",
    "Player": "Jeff Hoffman"
  },
  {
    "Rank": "579",
    "Player": "Drey Jameson"
  },
  {
    "Rank": "580",
    "Player": "Kenley Jansen#"
  },
  {
    "Rank": "581",
    "Player": "Griffin Jax"
  },
  {
    "Rank": "582",
    "Player": "Tommy Kahnle"
  },
  {
    "Rank": "583",
    "Player": "Casey Legumina"
  },
  {
    "Rank": "584",
    "Player": "Joe Mantiply"
  },
  {
    "Rank": "585",
    "Player": "Justin Martínez"
  },
  {
    "Rank": "586",
    "Player": "Phil Maton"
  },
  {
    "Rank": "587",
    "Player": "Tyler Matzek"
  },
  {
    "Rank": "588",
    "Player": "Juan Mejia"
  },
  {
    "Rank": "589",
    "Player": "Shelby Miller"
  },
  {
    "Rank": "590",
    "Player": "Hoby Milner"
  },
  {
    "Rank": "591",
    "Player": "Tyler Owens"
  },
  {
    "Rank": "592",
    "Player": "Andre Pallante"
  },
  {
    "Rank": "593",
    "Player": "Cionel Pérez"
  },
  {
    "Rank": "594",
    "Player": "A.J. Puk"
  },
  {
    "Rank": "595",
    "Player": "Trevor Richards"
  },
  {
    "Rank": "596",
    "Player": "Tyler Rogers"
  },
  {
    "Rank": "597",
    "Player": "Nick Sandlin"
  },
  {
    "Rank": "598",
    "Player": "John Schreiber"
  },
  {
    "Rank": "599",
    "Player": "Tanner Scott"
  },
  {
    "Rank": "600",
    "Player": "Ryan Thompson"
  },
  {
    "Rank": "601",
    "Player": "Ryan Walker"
  },
  {
    "Rank": "602",
    "Player": "Bryse Wilson"
  }
]