{
    "Batting Average": [
        {
            "Rank": "1.",
            "Player": "Judge \u2022 NYY",
            "Batting Average": ".396"
        },
        {
            "Rank": "2.",
            "Player": "Freeman \u2022 LAD",
            "Batting Average": ".366"
        },
        {
            "Rank": "3.",
            "Player": "Wilson \u2022 ATH",
            "Batting Average": ".354"
        },
        {
            "Rank": "4.",
            "Player": "Goldschmidt \u2022 NYY",
            "Batting Average": ".345"
        },
        {
            "Rank": "5.",
            "Player": "Kwan \u2022 CLE",
            "Batting Average": ".333"
        },
        {
            "Rank": "6.",
            "Player": "Aranda \u2022 TBR",
            "Batting Average": ".330"
        },
        {
            "Rank": "7.",
            "Player": "Donovan \u2022 STL",
            "Batting Average": ".329"
        },
        {
            "Rank": "8.",
            "Player": "Alonso \u2022 NYM",
            "Batting Average": ".324"
        },
        {
            "Rank": "9.",
            "Player": "Smith \u2022 TEX",
            "Batting Average": ".321"
        },
        {
            "Rank": "10.",
            "Player": "Machado \u2022 SDP",
            "Batting Average": ".319"
        }
    ],
    "On Base Percentage": [
        {
            "Rank": "1.",
            "Player": "Judge \u2022 NYY",
            "On Base Percentage": ".488"
        },
        {
            "Rank": "2.",
            "Player": "Alonso \u2022 NYM",
            "On Base Percentage": ".443"
        },
        {
            "Rank": "3.",
            "Player": "Freeman \u2022 LAD",
            "On Base Percentage": ".436"
        },
        {
            "Rank": "4.",
            "Player": "Ozuna \u2022 ATL",
            "On Base Percentage": ".425"
        },
        {
            "Rank": "5.",
            "Player": "Aranda \u2022 TBR",
            "On Base Percentage": ".424"
        },
        {
            "Rank": "6.",
            "Player": "Smith \u2022 ARI",
            "On Base Percentage": ".431"
        },
        {
            "Rank": "7.",
            "Player": "Smith \u2022 LAD",
            "On Base Percentage": ".415"
        },
        {
            "Rank": "8.",
            "Player": "Ohtani \u2022 LAD",
            "On Base Percentage": ".408"
        },
        {
            "Rank": "9.",
            "Player": "Perdomo \u2022 ARI",
            "On Base Percentage": ".406"
        },
        {
            "Rank": "10.",
            "Player": "Springer \u2022 TOR",
            "On Base Percentage": ".405"
        }
    ],
    "Slugging": [
        {
            "Rank": "1.",
            "Player": "Judge \u2022 NYY",
            "Slugging": ".743"
        },
        {
            "Rank": "2.",
            "Player": "Freeman \u2022 LAD",
            "Slugging": ".703"
        },
        {
            "Rank": "3.",
            "Player": "Ohtani \u2022 LAD",
            "Slugging": ".655"
        },
        {
            "Rank": "4.",
            "Player": "Alonso \u2022 NYM",
            "Slugging": ".627"
        },
        {
            "Rank": "5.",
            "Player": "Polanco \u2022 SEA",
            "Slugging": ".680"
        },
        {
            "Rank": "6.",
            "Player": "Hern\u00e1ndez \u2022 LAD",
            "Slugging": ".600"
        },
        {
            "Rank": "7.",
            "Player": "Bregman \u2022 BOS",
            "Slugging": ".587"
        },
        {
            "Rank": "8.",
            "Player": "Carroll \u2022 ARI",
            "Slugging": ".579"
        },
        {
            "Rank": "9.",
            "Player": "Raleigh \u2022 SEA",
            "Slugging": ".562"
        },
        {
            "Rank": "10.",
            "Player": "Tucker \u2022 CHC",
            "Slugging": ".559"
        }
    ],
    "Home Runs": [
        {
            "Rank": "1.",
            "Player": "Ohtani \u2022 LAD",
            "Home Runs": "12"
        },
        {
            "Rank": "",
            "Player": "Judge \u2022 NYY",
            "Home Runs": "12"
        },
        {
            "Rank": "",
            "Player": "Schwarber \u2022 PHI",
            "Home Runs": "12"
        },
        {
            "Rank": "",
            "Player": "Raleigh \u2022 SEA",
            "Home Runs": "12"
        },
        {
            "Rank": "5.",
            "Player": "Carroll \u2022 ARI",
            "Home Runs": "11"
        },
        {
            "Rank": "",
            "Player": "Su\u00e1rez \u2022 ARI",
            "Home Runs": "11"
        },
        {
            "Rank": "7.",
            "Player": "Tucker \u2022 CHC",
            "Home Runs": "10"
        },
        {
            "Rank": "",
            "Player": "Torkelson \u2022 DET",
            "Home Runs": "10"
        },
        {
            "Rank": "",
            "Player": "Grisham \u2022 NYY",
            "Home Runs": "10"
        },
        {
            "Rank": "",
            "Player": "Wood \u2022 WSN",
            "Home Runs": "10"
        }
    ],
    "Stolen Bases": [
        {
            "Rank": "1.",
            "Player": "Robert \u2022 CHW",
            "Stolen Bases": "15"
        },
        {
            "Rank": "",
            "Player": "Cruz \u2022 PIT",
            "Stolen Bases": "15"
        },
        {
            "Rank": "3.",
            "Player": "De La Cruz \u2022 CIN",
            "Stolen Bases": "14"
        },
        {
            "Rank": "4.",
            "Player": "Witt \u2022 KCR",
            "Stolen Bases": "13"
        },
        {
            "Rank": "5.",
            "Player": "Crow-Armstrong \u2022 CHC",
            "Stolen Bases": "12"
        },
        {
            "Rank": "6.",
            "Player": "Duran \u2022 BOS",
            "Stolen Bases": "11"
        },
        {
            "Rank": "",
            "Player": "Scott \u2022 STL",
            "Stolen Bases": "11"
        },
        {
            "Rank": "8.",
            "Player": "Tucker \u2022 CHC",
            "Stolen Bases": "10"
        },
        {
            "Rank": "",
            "Player": "Garcia \u2022 KCR",
            "Stolen Bases": "10"
        },
        {
            "Rank": "",
            "Player": "Ohtani \u2022 LAD",
            "Stolen Bases": "10"
        },
        {
            "Rank": "",
            "Player": "Edwards \u2022 MIA",
            "Stolen Bases": "10"
        },
        {
            "Rank": "",
            "Player": "Acu\u00f1a \u2022 NYM",
            "Stolen Bases": "10"
        }
    ]
}